bankid_sdk/__init__.py
bankid_sdk/_actions.py
bankid_sdk/_auth.py
bankid_sdk/_cancel.py
bankid_sdk/_client.py
bankid_sdk/_collect.py
bankid_sdk/_config.py
bankid_sdk/_hint_codes.py
bankid_sdk/_order.py
bankid_sdk/_requirement.py
bankid_sdk/_sign.py
bankid_sdk/_storage.py
bankid_sdk/_version.py
bankid_sdk/errors.py
bankid_sdk/py.typed
bankid_sdk/typing.py
bankid_sdk/utils.py
bankid_sdk/contrib/__init__.py
bankid_sdk/contrib/django/__init__.py
bankid_sdk/contrib/django/request.py
bankid_sdk/contrib/django/rest.py
bankid_sdk/contrib/django/storage.py
bankid_sdk/contrib/django/transaction.py
bankid_sdk-0.0.1.dist-info/METADATA
bankid_sdk-0.0.1.dist-info/WHEEL
bankid_sdk-0.0.1.dist-info/licenses/LICENSE
bankid_sdk-0.0.1.dist-info/RECORD
