Metadata-Version: 2.1
Name: bankid-sdk
Version: 0.0.1
Summary: A Python SDK for BankID
Project-URL: Homepage, https://github.com/5monkeys/bankid-sdk
Project-URL: Source, https://github.com/5monkeys/bankid-sdk
Project-URL: Tracker, https://github.com/5monkeys/bankid-sdk/issues
Author-email: Jonas Lundberg <jonas@5monkeys.se>
License-Expression: BSD-3-Clause
License-File: LICENSE
Keywords: bankid,client,django,rest
Classifier: Development Status :: 4 - Beta
Classifier: Framework :: Django
Classifier: Framework :: Django :: 4.1
Classifier: Framework :: Django :: 4.2
Classifier: Framework :: Django :: 5.0
Classifier: Intended Audience :: Developers
Classifier: License :: OSI Approved :: BSD License
Classifier: Operating System :: OS Independent
Classifier: Programming Language :: Python :: 3 :: Only
Classifier: Programming Language :: Python :: 3.9
Classifier: Programming Language :: Python :: 3.10
Classifier: Programming Language :: Python :: 3.11
Classifier: Programming Language :: Python :: 3.12
Classifier: Typing :: Typed
Requires-Python: >=3.9
Requires-Dist: abcattrs
Requires-Dist: httpx
Provides-Extra: dev
Requires-Dist: bankid-sdk[test]; extra == 'dev'
Requires-Dist: mypy; extra == 'dev'
Requires-Dist: pre-commit; extra == 'dev'
Provides-Extra: django
Requires-Dist: django; extra == 'django'
Provides-Extra: test
Requires-Dist: bankid-sdk[django]; extra == 'test'
Requires-Dist: dirty-equals; extra == 'test'
Requires-Dist: django-stubs; extra == 'test'
Requires-Dist: freezegun; extra == 'test'
Requires-Dist: pytest; extra == 'test'
Requires-Dist: pytest-asyncio; extra == 'test'
Requires-Dist: pytest-cov; extra == 'test'
Requires-Dist: pytest-django; extra == 'test'
Requires-Dist: pytest-randomly; extra == 'test'
Requires-Dist: respx; extra == 'test'
